chunk_factory/__init__.py
chunk_factory/chunker.py
chunk_factory/eval/__init__.py
chunk_factory/eval/eval_chunker.py
chunk_factory/module/__init__.py
chunk_factory/module/baseChunker.py
chunk_factory/module/densexChunker.py
chunk_factory/module/lumberChunker.py
chunk_factory/module/mspChunker.py
chunk_factory/module/pplChunker.py
chunk_factory/utils/__init__.py
chunk_factory/utils/llm.py
chunk_factory/utils/metric.py
chunk_factory/utils/prompts.py
chunk_factory/utils/util.py
chunk_factory-0.1.1.dist-info/METADATA
chunk_factory-0.1.1.dist-info/WHEEL
chunk_factory-0.1.1.dist-info/top_level.txt
chunk_factory-0.1.1.dist-info/RECORD
