Metadata-Version: 2.4
Name: chunk-factory
Version: 0.1.1
Summary: An efficient chunking library that integrates traditional and advanced methods, with real-time evaluation of chunking results.
Home-page: https://github.com/hjandlm/Chunk-Factory
Author: Jie Huang
Author-email: hjie97bi@gmail.com
License: MIT
Keywords: python,windows,mac,linux,text chunk,chunker,eval text chunk,LLM chunk,openai,gemini
Classifier: License :: OSI Approved :: MIT License
Classifier: Programming Language :: Python
Classifier: Programming Language :: Python :: 3
Classifier: Programming Language :: Python :: 3.10
Classifier: Programming Language :: Python :: 3.11
Classifier: Programming Language :: Python :: 3.12
Classifier: Programming Language :: Python :: Implementation :: CPython
Classifier: Programming Language :: Python :: Implementation :: PyPy
Classifier: Framework :: Jupyter
Classifier: Operating System :: MacOS
Classifier: Operating System :: Microsoft
Classifier: Operating System :: Microsoft :: Windows
Classifier: Operating System :: Microsoft :: Windows :: Windows 10
Classifier: Operating System :: Microsoft :: Windows :: Windows 11
Classifier: Operating System :: Unix
Requires-Python: >=3.10.0
Requires-Dist: transformers>=4.49.0
Requires-Dist: tiktoken>=0.9.0
Requires-Dist: seaborn>=0.13.2
Requires-Dist: matplotlib>=3.10.1
Requires-Dist: sentence-transformers>=4.0.2
Requires-Dist: pandas>=2.2.3
Requires-Dist: openai>=1.68.2
Requires-Dist: google-genai>=1.9.0
Requires-Dist: jieba>=0.42.1
Requires-Dist: nltk>=3.9.1
Requires-Dist: tqdm>=4.67.1
Dynamic: author
Dynamic: author-email
Dynamic: classifier
Dynamic: description
Dynamic: description-content-type
Dynamic: home-page
Dynamic: keywords
Dynamic: license
Dynamic: requires-dist
Dynamic: requires-python
Dynamic: summary
